mdtex2html/__init__.py
mdtex2html-1.3.1.dist-info/LICENSE
mdtex2html-1.3.1.dist-info/METADATA
mdtex2html-1.3.1.dist-info/WHEEL
mdtex2html-1.3.1.dist-info/top_level.txt
mdtex2html-1.3.1.dist-info/RECORD
