Metadata-Version: 2.1
Name: mdtex2html
Version: 1.3.1
Summary: library to convert Markdown with included LaTeX-Formulas to HTML with MathML
Home-page: https://github.com/polarwinkel/mdtex2html
Author: Dirk Winkel
Author-email: it@polarwinkel.de
Project-URL: Bug Reports, https://github.com/polarwinkel/mdtex2html/issues
Project-URL: Source, https://github.com/polarwinkel/mdtex2html
Keywords: TeX,LaTeX,Markdown,HTML markdown2html,latex2mathml
Classifier: Development Status :: 5 - Production/Stable
Classifier: Intended Audience :: Developers
Classifier: Intended Audience :: Education
Classifier: Topic :: Text Processing :: Markup
Classifier: Topic :: Text Processing :: Markup :: HTML
Classifier: Topic :: Text Processing :: Markup :: LaTeX
Classifier: Topic :: Text Processing :: Markup :: Markdown
Classifier: License :: OSI Approved :: GNU Lesser General Public License v2 or later (LGPLv2+)
Classifier: Programming Language :: Python :: 3
Classifier: Programming Language :: Python :: 3.7
Classifier: Programming Language :: Python :: 3.8
Classifier: Programming Language :: Python :: 3.9
Classifier: Programming Language :: Python :: 3 :: Only
Requires-Python: >=3.7, <4
License-File: LICENSE
Requires-Dist: markdown
Requires-Dist: latex2mathml
